promisio/__init__.py
promisio-0.1.1.dist-info/METADATA
promisio-0.1.1.dist-info/WHEEL
promisio-0.1.1.dist-info/top_level.txt
promisio-0.1.1.dist-info/RECORD
