Metadata-Version: 2.1
Name: promisio
Version: 0.1.1
Summary: JavaScript-style async programming for Python.
Home-page: https://github.com/miguelgrinberg/promisio
Author: Miguel Grinberg
Author-email: miguel.grinberg@gmail.com
License: UNKNOWN
Project-URL: Bug Tracker, https://github.com/miguelgrinberg/promisio/issues
Platform: UNKNOWN
Classifier: Intended Audience :: Developers
Classifier: Programming Language :: Python :: 3
Classifier: License :: OSI Approved :: MIT License
Classifier: Operating System :: OS Independent
Requires-Python: >=3.6
